multigait/CAD/__init__.py
multigait/CAD/base_cad.py
multigait/CAD/cad.py
multigait/CAD/utils/__init__.py
multigait/CAD/utils/cad_utils.py
multigait/GSD/GSD1.py
multigait/GSD/GSD2.py
multigait/GSD/GSD3.py
multigait/GSD/GSD4.py
multigait/GSD/GSD5.py
multigait/GSD/__init__.py
multigait/GSD/base_gsd.py
multigait/GSD/utils/ActivityCounts.py
multigait/GSD/utils/GSD1_utils.py
multigait/GSD/utils/GSD3_utils.py
multigait/GSD/utils/__init__.py
multigait/GSD/utils/cart_to_spher.py
multigait/GSD/utils/cwb.py
multigait/GSD/utils/gravity_remove_butter.py
multigait/GSD/utils/merge_bouts.py
multigait/ICD/ICD1.py
multigait/ICD/ICD2.py
multigait/ICD/ICD3.py
multigait/ICD/ICD4.py
multigait/ICD/ICD5.py
multigait/ICD/ICD6.py
multigait/ICD/__init__.py
multigait/ICD/base_ic.py
multigait/ICD/utils/__init__.py
multigait/ICD/utils/auto_cov_unbiased.py
multigait/ICD/utils/dominant_frequency.py
multigait/ICD/utils/dtwDasGupta.py
multigait/ICD/utils/find_maxima.py
multigait/ICD/utils/find_minima.py
multigait/ICD/utils/peakfind.py
multigait/ICD/utils/zero_crossings.py
multigait/SL/SL1.py
multigait/SL/SL2.py
multigait/SL/SL3.py
multigait/SL/__init__.py
multigait/SL/base_sl.py
multigait/SL/utils/SL_utils.py
multigait/SL/utils/__init__.py
multigait/WS/__init__.py
multigait/WS/base_ws.py
multigait/WS/walking_speed.py
multigait/__init__.py
multigait/aggregation/__init__.py
multigait/aggregation/_aggregator_base.py
multigait/aggregation/_generic_aggregator.py
multigait/aggregation/_lab_aggregator.py
multigait/data/__init__.py
multigait/data/base_data.py
multigait/data_loader/__init__.py
multigait/data_loader/cwa_data_loader.py
multigait/interpolation_ts/__init__.py
multigait/interpolation_ts/interpolation.py
multigait/pipeline/__init__.py
multigait/pipeline/iterator.py
multigait/pipeline/multimobility_pipeline.py
multigait/pipeline/pipeline_base.py
multigait/pipeline/utils/__init__.py
multigait/pipeline/utils/_operations.py
multigait/pipeline/utils/_stride_filtering.py
multigait-0.2.0.dist-info/METADATA
multigait-0.2.0.dist-info/WHEEL
multigait-0.2.0.dist-info/licenses/LICENSE
multigait-0.2.0.dist-info/RECORD
