Metadata-Version: 2.4
Name: multigait
Version: 0.2.0
Summary: MultiGait: Real-World Gait Pipeline for Wrist-Worn Devices
License-File: LICENSE
Author: DMegaritis
Author-email: d.megaritis@northumbria.ac.uk
Requires-Python: >=3.9,<3.14
Classifier: Programming Language :: Python :: 3
Classifier: Programming Language :: Python :: 3.9
Classifier: Programming Language :: Python :: 3.10
Classifier: Programming Language :: Python :: 3.11
Classifier: Programming Language :: Python :: 3.12
Classifier: Programming Language :: Python :: 3.13
Requires-Dist: matplotlib (>=3.7.2,<4)
Requires-Dist: mobgap (>=1.0.0,<2.0.0)
Requires-Dist: numpy (>=1.25.2)
Requires-Dist: pandas (>=2.2.0)
Requires-Dist: typing-extensions (>=4.15.0,<5.0.0)
